docpack_confluence/__init__.py
docpack_confluence/_version.py
docpack_confluence/api.py
docpack_confluence/constants.py
docpack_confluence/crawler.py
docpack_confluence/exporter.py
docpack_confluence/one.py
docpack_confluence/pack.py
docpack_confluence/page.py
docpack_confluence/paths.py
docpack_confluence/selector.py
docpack_confluence/shortcuts.py
docpack_confluence/type_hint.py
docpack_confluence/utils.py
docpack_confluence/vendor/__init__.py
docpack_confluence/vendor/more_itertools.py
docpack_confluence/vendor/pytest_cov_helper.py
docpack_confluence-0.1.3.dist-info/AUTHORS.rst
docpack_confluence-0.1.3.dist-info/LICENSE.txt
docpack_confluence-0.1.3.dist-info/METADATA
docpack_confluence-0.1.3.dist-info/WHEEL
docpack_confluence-0.1.3.dist-info/RECORD
