Metadata-Version: 2.3
Name: docpack_confluence
Version: 0.1.3
Summary: Batch export Confluence pages to AI-ready Markdown/XML formats with gitignore-style filtering.
License: MIT
Author: Sanhe Hu
Author-email: husanhe@email.com
Maintainer: Sanhe Hu
Maintainer-email: husanhe@email.com
Requires-Python: >=3.10,<4.0
Classifier: License :: OSI Approved :: MIT License
Classifier: Programming Language :: Python :: 3
Classifier: Programming Language :: Python :: 3.10
Classifier: Programming Language :: Python :: 3.11
Classifier: Programming Language :: Python :: 3.12
Classifier: Programming Language :: Python :: 3.13
Provides-Extra: auto
Provides-Extra: dev
Provides-Extra: doc
Provides-Extra: test
Requires-Dist: Sphinx (>=7.4.7,<8.0.0) ; extra == "doc"
Requires-Dist: atlas_doc_parser (>=1.0.1,<2.0.0)
Requires-Dist: build (>=1.2.1,<2.0.0) ; extra == "dev"
Requires-Dist: diskcache (>=5.6.3,<6.0.0)
Requires-Dist: docfly (==3.0.0) ; extra == "doc"
Requires-Dist: func_args (>=1.0.1,<2.0.0)
Requires-Dist: furo (==2024.8.6) ; extra == "doc"
Requires-Dist: home-secret-toml (>=0.2.1,<1.0.0) ; extra == "test"
Requires-Dist: ipython (>=8.18.1,<8.19.0) ; extra == "doc"
Requires-Dist: nbsphinx (>=0.8.12,<1.0.0) ; extra == "doc"
Requires-Dist: orjson (>=3.10.0,<4.0.0)
Requires-Dist: pygments (>=2.18.0,<3.0.0) ; extra == "doc"
Requires-Dist: pytest (>=8.2.2,<9.0.0) ; extra == "test"
Requires-Dist: pytest-cov (>=6.0.0,<7.0.0) ; extra == "test"
Requires-Dist: rich (>=13.8.1,<14.0.0) ; extra == "dev"
Requires-Dist: rstobj (==1.2.1) ; extra == "doc"
Requires-Dist: sanhe-confluence-sdk (>=0.1.3,<1.0.0)
Requires-Dist: sphinx-copybutton (>=0.5.2,<1.0.0) ; extra == "doc"
Requires-Dist: sphinx-design (>=0.6.1,<1.0.0) ; extra == "doc"
Requires-Dist: sphinx-jinja (>=2.0.2,<3.0.0) ; extra == "doc"
Requires-Dist: twine (>=6.0.0,<7.0.0) ; extra == "dev"
Requires-Dist: wheel (>=0.45.0,<1.0.0) ; extra == "dev"
Project-URL: Changelog, https://github.com/MacHu-GWU/docpack_confluence-project/blob/main/release-history.rst
Project-URL: Documentation, https://docpack-confluence.readthedocs.io/en/latest/
Project-URL: Download, https://pypi.org/pypi/docpack-confluence#files
Project-URL: Homepage, https://github.com/MacHu-GWU/docpack_confluence-project
Project-URL: Issues, https://github.com/MacHu-GWU/docpack_confluence-project/issues
Project-URL: Repository, https://github.com/MacHu-GWU/docpack_confluence-project
